CHANGES.txt
LICENSE.txt
MANIFEST.in
README.txt
setup.py
bin/mass_rename
docs/info.txt
mass_rename/__init__.py
mass_rename.egg-info/PKG-INFO
mass_rename.egg-info/SOURCES.txt
mass_rename.egg-info/dependency_links.txt
mass_rename.egg-info/top_level.txt