Metadata-Version: 1.0
Name: mass-rename
Version: 0.0.1
Summary: Files group rename tool
Home-page: https://github.com/carlesso/mass_rename
Author: Enrico Carlesso
Author-email: enricocarlesso@gmail.com
License: LICENSE.txt
Platform: UNKNOWN
